pyrx.cpython-310-x86_64-linux-gnu.so
xapu-1.0.2.0.dist-info/METADATA
xapu-1.0.2.0.dist-info/WHEEL
xapu-1.0.2.0.dist-info/top_level.txt
xapu-1.0.2.0.dist-info/RECORD
