Metadata-Version: 2.1
Name: xapu
Version: 1.0.2.0
Summary: Python RandomX hashing module
Home-page: UNKNOWN
Author: vyomw
Author-email: vyomwankhede@gmail.com
License: UNKNOWN
Platform: UNKNOWN
